MANIFEST.in
NEWS.txt
README.rst
setup.py
fabby/__init__.py
fabby/canvas2D.py
fabby/canvas3D.py
fabby/example.py
fabby/gcode.py
fabby/producer.py
fabby/shape2D.py
fabby/shape3D.py
fabby.egg-info/PKG-INFO
fabby.egg-info/SOURCES.txt
fabby.egg-info/dependency_links.txt
fabby.egg-info/entry_points.txt
fabby.egg-info/not-zip-safe
fabby.egg-info/top_level.txt