Metadata-Version: 1.0
Name: fabby
Version: 0.01
Summary: A gcode generator to 3D print objects, directly from a python based model. Forget slicers, and build stuff directly from code !
Home-page: https://github.com/madlag/fabby
Author: Francois Lagunas
Author-email: francois.lagunas@gmail.com
License: BSD
Keywords: 3d printing reprap gcode
Platform: UNKNOWN
